pythonproject1/__init__.py
ailecs_nightwatch-0.1.0.dist-info/METADATA
ailecs_nightwatch-0.1.0.dist-info/WHEEL
ailecs_nightwatch-0.1.0.dist-info/top_level.txt
ailecs_nightwatch-0.1.0.dist-info/RECORD
