Metadata-Version: 2.1
Name: ailecs-nightwatch
Version: 0.1.0
Summary: Default template for PDM package
Author-email: aw <ailecs-lab-l@monash.edu>
License: MIT
Requires-Python: ==3.12.*
